mercator/__init__.py
mercator/client.py
mercator/config.py
mercator/exceptions.py
mercator/local_mode.py
mercator/session.py
mercator/transport.py
mercator/api/__init__.py
mercator/api/chat.py
mercator_sdk-0.2.1.dist-info/licenses/LICENSE
mercator_sdk-0.2.1.dist-info/METADATA
mercator_sdk-0.2.1.dist-info/WHEEL
mercator_sdk-0.2.1.dist-info/top_level.txt
mercator_sdk-0.2.1.dist-info/RECORD
