Metadata-Version: 2.4
Name: mercator-sdk
Version: 0.2.1
Summary: Python SDK for Mercator - Governed LLM access with automatic policy enforcement
Author-email: Mercator Team <team@mercator.dev>
License: MIT License
Project-URL: Homepage, https://www.onmercator.com
Project-URL: Documentation, https://www.docs.onmercator.com
Project-URL: Repository, https://github.com/codeeater800/mercator-one
Project-URL: Issues, https://www.issues.onmercator.com
Keywords: llm,governance,openai,anthropic,policy,compliance,ai
Classifier: Development Status :: 3 - Alpha
Classifier: Intended Audience :: Developers
Classifier: License :: OSI Approved :: MIT License
Classifier: Programming Language :: Python :: 3
Classifier: Programming Language :: Python :: 3.8
Classifier: Programming Language :: Python :: 3.9
Classifier: Programming Language :: Python :: 3.10
Classifier: Programming Language :: Python :: 3.11
Classifier: Programming Language :: Python :: 3.12
Classifier: Topic :: Software Development :: Libraries :: Python Modules
Classifier: Topic :: Scientific/Engineering :: Artificial Intelligence
Requires-Python: >=3.8
License-File: LICENSE
Requires-Dist: httpx>=0.25.0
Provides-Extra: dev
Requires-Dist: pytest>=7.4.0; extra == "dev"
Requires-Dist: pytest-cov>=4.1.0; extra == "dev"
Requires-Dist: pytest-asyncio>=0.21.0; extra == "dev"
Requires-Dist: black>=23.7.0; extra == "dev"
Requires-Dist: ruff>=0.0.285; extra == "dev"
Requires-Dist: mypy>=1.5.0; extra == "dev"
Dynamic: license-file
